ZnPyobject/__init__.py
ZnPyobject/znpyoperation.py
ZnPyobject-0.0.2.dist-info/METADATA
ZnPyobject-0.0.2.dist-info/WHEEL
ZnPyobject-0.0.2.dist-info/top_level.txt
ZnPyobject-0.0.2.dist-info/zip-safe
ZnPyobject-0.0.2.dist-info/RECORD
